Metadata-Version: 2.1
Name: SimpleWhois
Version: 0.0.3
Summary: This module implements WHOIS protocol and performs WHOIS requests.
Home-page: https://github.com/mauricelambert/SimpleWhois
Download-URL: https://mauricelambert.github.io/info/python/code/SimpleWhois.pyz
Author: Maurice Lambert
Author-email: Maurice Lambert <mauricelambert434@gmail.com>
Maintainer: Maurice Lambert
Maintainer-email: Maurice Lambert <mauricelambert434@gmail.com>
License: GPL-3.0 License
Project-URL: Github, https://github.com/mauricelambert/SimpleWhois
Project-URL: Documentation, https://mauricelambert.github.io/info/python/code/SimpleWhois.html
Project-URL: Python Executable, https://mauricelambert.github.io/info/python/code/SimpleWhois.pyz
Project-URL: Windows Executable, https://mauricelambert.github.io/info/python/code/SimpleWhois.exe
Keywords: WHOIS,RFC,Network,Domain,Registar
Platform: Windows
Platform: Linux
Platform: MacOS
Classifier: Topic :: System
Classifier: Topic :: Software Development :: Libraries
Classifier: Environment :: Console
Classifier: Topic :: System :: Shells
Classifier: Operating System :: POSIX
Classifier: Natural Language :: English
Classifier: Topic :: System :: Networking
Classifier: Programming Language :: Python
Classifier: Intended Audience :: Developers
Classifier: Topic :: System :: System Shells
Classifier: Operating System :: MacOS :: MacOS X
Classifier: Programming Language :: Python :: 3.8
Classifier: Operating System :: Microsoft :: Windows
Classifier: Topic :: System :: Systems Administration
Classifier: Development Status :: 5 - Production/Stable
Classifier: Intended Audience :: System Administrators
Classifier: License :: OSI Approved :: GNU General Public License v3 or later (GPLv3+)
Requires-Python: >=3.8
License-File: LICENSE.txt
